ClimateDataAnalyzer/ClimateDataObj.py
ClimateDataAnalyzer/__init__.py
ClimateDataAnalyzer/_mpl_tk.py
ClimateDataAnalyzer/cda.py
ClimateDataAnalyzer/dbCoupler.py
ClimateDataAnalyzer/fips2db.py
ClimateDataAnalyzer/guiMain.py
ClimateDataAnalyzer/guiPlot.py
ClimateDataAnalyzer/guiStyle.py
ClimateDataAnalyzer/noaa.py
ClimateDataAnalyzer/extra/arrow-lf16x16.gif
ClimateDataAnalyzer/extra/arrow-rt16x16.gif
ClimateDataAnalyzer/extra/fips_codes.db
climatedataanalyzer-0.0.5.dist-info/METADATA
climatedataanalyzer-0.0.5.dist-info/WHEEL
climatedataanalyzer-0.0.5.dist-info/licenses/LICENSE
climatedataanalyzer-0.0.5.dist-info/RECORD
